idds/__init__.py
idds/version.py
idds/agents/__init__.py
idds/agents/main.py
idds/agents/archive/__init__.py
idds/agents/archive/archiver.py
idds/agents/archive/run_archive.py
idds/agents/carrier/__init__.py
idds/agents/carrier/finisher.py
idds/agents/carrier/poller.py
idds/agents/carrier/receiver.py
idds/agents/carrier/submitter.py
idds/agents/carrier/trigger.py
idds/agents/carrier/utils.py
idds/agents/clerk/__init__.py
idds/agents/clerk/clerk.py
idds/agents/common/__init__.py
idds/agents/common/baseagent.py
idds/agents/common/timerscheduler.py
idds/agents/common/timertask.py
idds/agents/common/cache/__init__.py
idds/agents/common/cache/redis.py
idds/agents/common/eventbus/__init__.py
idds/agents/common/eventbus/baseeventbusbackend.py
idds/agents/common/eventbus/baseeventbusbackendopt.py
idds/agents/common/eventbus/dbeventbusbackend.py
idds/agents/common/eventbus/event.py
idds/agents/common/eventbus/eventbus.py
idds/agents/common/eventbus/msgeventbusbackend.py
idds/agents/common/plugins/__init__.py
idds/agents/common/plugins/messaging.py
idds/agents/conductor/__init__.py
idds/agents/conductor/conductor.py
idds/agents/conductor/consumer.py
idds/agents/coordinator/__init__.py
idds/agents/coordinator/coordinator.py
idds/agents/marshaller/__init__.py
idds/agents/marshaller/marshaller.py
idds/agents/transformer/__init__.py
idds/agents/transformer/transformer.py
idds/agents/transporter/__init__.py
idds/agents/transporter/transporter.py
idds/api/__init__.py
idds/api/catalog.py
idds/api/collections.py
idds/api/contents.py
idds/api/processings.py
idds/api/requests.py
idds/api/transforms.py
idds/core/__init__.py
idds/core/catalog.py
idds/core/commands.py
idds/core/events.py
idds/core/health.py
idds/core/messages.py
idds/core/processings.py
idds/core/requests.py
idds/core/throttlers.py
idds/core/transforms.py
idds/core/workprogress.py
idds/orm/__init__.py
idds/orm/collections.py
idds/orm/commands.py
idds/orm/contents.py
idds/orm/events.py
idds/orm/health.py
idds_server-2.0.9.dist-info/LICENSE.rst
idds_server-2.0.9.dist-info/METADATA
idds_server-2.0.9.dist-info/WHEEL
idds_server-2.0.9.dist-info/top_level.txt
idds_server-2.0.9.dist-info/RECORD
