Metadata-Version: 2.1
Name: idds-server
Version: 2.0.9
Summary: intelligent Data Delivery Service(iDDS) Package
Author: IRIS-HEP Team
Author-email: atlas-adc-panda@cern.ch
License: GPL
Project-URL: Documentation, https://github.com/HSF/iDDS/wiki
Project-URL: Source, https://github.com/HSF/iDDS
Classifier: Development Status :: 5 - Production/Stable
Classifier: Intended Audience :: Developers
Classifier: Natural Language :: English
Classifier: Programming Language :: Python :: 3.6
Requires-Python: >=3.6
License-File: LICENSE.rst
Requires-Dist: pip
Requires-Dist: argcomplete
Requires-Dist: requests
Requires-Dist: SQLAlchemy ==1.4.46
Requires-Dist: urllib3
Requires-Dist: retrying
Requires-Dist: mod-wsgi
Requires-Dist: flask
Requires-Dist: futures
Requires-Dist: stomp.py
Requires-Dist: cx-Oracle
Requires-Dist: unittest2
Requires-Dist: pep8
Requires-Dist: flake8
Requires-Dist: pytest
Requires-Dist: nose
Requires-Dist: sphinx
Requires-Dist: recommonmark
Requires-Dist: sphinx-rtd-theme
Requires-Dist: nevergrad
Requires-Dist: psycopg2-binary
Requires-Dist: pyjwt
Requires-Dist: cryptography
Requires-Dist: redis
Requires-Dist: alembic
Requires-Dist: deepdiff
Requires-Dist: pyzmq
Requires-Dist: oic
Requires-Dist: lsst-ctrl-bps
Requires-Dist: idds-common ==2.0.9
Requires-Dist: idds-workflow ==2.0.9
Requires-Dist: idds-client ==2.0.9
Provides-Extra: mysql
Requires-Dist: mysqlclient ; extra == 'mysql'
